Metadata-Version: 2.1
Name: ph4-gas
Version: 0.0.1
Summary: Ph4 Sensirion Gas Index algorithm in Python 
Home-page: https://github.com/ph4r05/ph4-sensirion-gas-index-algorithm-py
Author: Dusan Klinec
Author-email: dusan.klinec@gmail.com
License: MIT
Classifier: Development Status :: 3 - Alpha
Classifier: Intended Audience :: Developers
Classifier: Programming Language :: Python
Classifier: Programming Language :: Python :: 2
Classifier: Programming Language :: Python :: 2.6
Classifier: Programming Language :: Python :: 2.7
Classifier: Programming Language :: Python :: 3
Classifier: Programming Language :: Python :: 3.3
Classifier: Programming Language :: Python :: 3.4
Classifier: Programming Language :: Python :: 3.5
Provides-Extra: dev
Provides-Extra: docs
License-File: LICENSE
